{
    "gridSize": 6,
    "solutions": [
        {
            "word": "--slip",
            "hintImages": [
                {
                    "sprite": {
                        "instanceID": 57870
                    },
                    "license": "Pexels",
                    "attribution": "",
                    "UUID": "14b8c64bfe11b489caab7b87e3e0c507"
                }
            ]
        },
        {
            "word": "-stone",
            "hintImages": [
                {
                    "sprite": {
                        "instanceID": 58392
                    },
                    "license": "Pexels",
                    "attribution": "",
                    "UUID": "2e14fbdc8e70a4249b58a4dfed431274"
                },
                {
                    "sprite": {
                        "instanceID": 58816
                    },
                    "license": "Pexels",
                    "attribution": "",
                    "UUID": ""
                }
            ]
        },
        {
            "word": "-naive",
            "hintImages": [
                {
                    "sprite": {
                        "instanceID": 61190
                    },
                    "license": "Pexels",
                    "attribution": "",
                    "UUID": "71ebf276c80ed4fada795800b26e944b"
                }
            ]
        },
        {
            "word": "barter",
            "hintImages": [
                {
                    "sprite": {
                        "instanceID": 60390
                    },
                    "license": "Pexels",
                    "attribution": "",
                    "UUID": "470c73ef4f3964640853c1dfde69dd89"
                }
            ]
        },
        {
            "word": "river-",
            "hintImages": [
                {
                    "sprite": {
                        "instanceID": 60654
                    },
                    "license": "Pexels",
                    "attribution": "",
                    "UUID": "c91a41375edba4397bfa8306c2266dfd"
                }
            ]
        },
        {
            "word": "alert-",
            "hintImages": [
                {
                    "sprite": {
                        "instanceID": 57130
                    },
                    "license": "Pexels",
                    "attribution": "",
                    "UUID": "1bdeec3e5f0cb42b2a31d1a3ada20633"
                }
            ]
        },
        {
            "word": "---bra",
            "hintImages": [
                {
                    "sprite": {
                        "instanceID": 56500
                    },
                    "license": "Pexels",
                    "attribution": "",
                    "UUID": "91b9bdd4be6f3435685f0903cd17b227"
                }
            ]
        },
        {
            "word": "-snail",
            "hintImages": [
                {
                    "sprite": {
                        "instanceID": 61192
                    },
                    "license": "Pexels",
                    "attribution": "Kenneth",
                    "UUID": "33fd5d66794b44e10903d93e4e124076"
                }
            ]
        },
        {
            "word": "starve",
            "hintImages": [
                {
                    "sprite": {
                        "instanceID": 61194
                    },
                    "license": "Pexels",
                    "attribution": "",
                    "UUID": "40d1261e4f54a48f987d89791ec429ae"
                }
            ]
        },
        {
            "word": "loiter",
            "hintImages": [
                {
                    "sprite": {
                        "instanceID": 55686
                    },
                    "license": "Pexels",
                    "attribution": "",
                    "UUID": "3f4c5a089254340fbb3bf0c1cdfafa9c"
                },
                {
                    "sprite": {
                        "instanceID": 56294
                    },
                    "license": "Pexels",
                    "attribution": "",
                    "UUID": ""
                }
            ]
        },
        {
            "word": "invert",
            "hintImages": [
                {
                    "sprite": {
                        "instanceID": 56784
                    },
                    "license": "Pexels",
                    "attribution": "",
                    "UUID": "0214bfb68238c4f63a948a7656fe4aa8"
                }
            ]
        },
        {
            "word": "peer--",
            "hintImages": [
                {
                    "sprite": {
                        "instanceID": 56964
                    },
                    "license": "Pexels",
                    "attribution": "",
                    "UUID": "4245cde6dfd6d49f7aca8ce1c4688ed3"
                }
            ]
        }
    ],
    "extraLetters": "trynmoupkqal"
}